{
"autoplayBgm":false,"autoplayBgs":false,"battleback1Name":"","battleback2Name":"","bgm":{"name":"","pan":0,"pitch":100,"volume":90},"bgs":{"name":"","pan":0,"pitch":100,"volume":90},"disableDashing":false,"displayName":"","encounterList":[],"encounterStep":30,"height":13,"note":"","parallaxLoopX":false,"parallaxLoopY":false,"parallaxName":"","parallaxShow":true,"parallaxSx":0,"parallaxSy":0,"scrollType":0,"specifyBattleback":false,"tilesetId":1,"width":17,
"data":[0,0,0,0,0,0,0,0,0,0,0,0,0,0,0,0,0,0,0,0,0,0,0,0,0,0,0,0,0,0,0,0,0,0,0,0,0,0,0,0,0,0,0,0,0,0,0,0,0,0,0,0,0,0,0,0,0,0,0,0,0,0,0,0,0,0,0,0,0,0,0,0,0,0,0,0,0,0,0,0,0,0,0,0,0,0,0,0,0,0,0,0,0,0,0,0,0,0,0,0,0,0,0,0,0,0,0,0,0,0,0,0,0,0,0,0,0,0,0,0,0,0,0,0,0,0,0,0,0,0,0,0,0,0,0,0,0,0,0,0,0,0,0,0,0,0,0,0,0,0,0,0,0,0,0,0,0,0,0,0,0,0,0,0,0,0,0,0,0,0,0,0,0,0,0,0,0,0,0,0,0,0,0,0,0,0,0,0,0,0,0,0,0,0,0,0,0,0,0,0,0,0,0,0,0,0,0,0,0,0,0,0,0,0,0,0,0,0,0,0,0,0,0,0,0,0,0,0,0,0,0,0,0,0,0,0,0,0,0,0,0,0,0,0,0,0,0,0,0,0,0,0,0,0,0,0,0,0,0,0,0,0,0,0,0,0,0,0,0,0,0,0,0,0,0,0,0,0,0,0,0,0,0,0,0,0,0,0,0,0,0,0,0,0,0,0,0,0,0,0,0,0,0,0,0,0,0,0,0,0,0,0,0,0,0,0,0,0,0,0,0,0,0,0,0,0,0,0,0,0,0,0,0,0,0,0,0,0,0,0,0,0,0,0,0,0,0,0,0,0,0,0,0,0,0,0,0,0,0,0,0,0,0,0,0,0,0,0,0,0,0,0,0,0,0,0,0,0,0,0,0,0,0,0,0,0,0,0,0,0,0,0,0,0,0,0,0,0,0,0,0,0,0,0,0,0,0,0,0,0,0,0,0,0,0,0,0,0,0,0,0,0,0,0,0,0,0,0,0,0,0,0,0,0,0,0,0,0,0,0,0,0,0,0,0,0,0,0,0,0,0,0,0,0,0,0,0,0,0,0,0,0,0,0,0,0,0,0,0,0,0,0,0,0,0,0,0,0,0,0,0,0,0,0,0,0,0,0,0,0,0,0,0,0,0,0,0,0,0,0,0,0,0,0,0,0,0,0,0,0,0,0,0,0,0,0,0,0,0,0,0,0,0,0,0,0,0,0,0,0,0,0,0,0,0,0,0,0,0,0,0,0,0,0,0,0,0,0,0,0,0,0,0,0,0,0,0,0,0,0,0,0,0,0,0,0,0,0,0,0,0,0,0,0,0,0,0,0,0,0,0,0,0,0,0,0,0,0,0,0,0,0,0,0,0,0,0,0,0,0,0,0,0,0,0,0,0,0,0,0,0,0,0,0,0,0,0,0,0,0,0,0,0,0,0,0,0,0,0,0,0,0,0,0,0,0,0,0,0,0,0,0,0,0,0,0,0,0,0,0,0,0,0,0,0,0,0,0,0,0,0,0,0,0,0,0,0,0,0,0,0,0,0,0,0,0,0,0,0,0,0,0,0,0,0,0,0,0,0,0,0,0,0,0,0,0,0,0,0,0,0,0,0,0,0,0,0,0,0,0,0,0,0,0,0,0,0,0,0,0,0,0,0,0,0,0,0,0,0,0,0,0,0,0,0,0,0,0,0,0,0,0,0,0,0,0,0,0,0,0,0,0,0,0,0,0,0,0,0,0,0,0,0,0,0,0,0,0,0,0,0,0,0,0,0,0,0,0,0,0,0,0,0,0,0,0,0,0,0,0,0,0,0,0,0,0,0,0,0,0,0,0,0,0,0,0,0,0,0,0,0,0,0,0,0,0,0,0,0,0,0,0,0,0,0,0,0,0,0,0,0,0,0,0,0,0,0,0,0,0,0,0,0,0,0,0,0,0,0,0,0,0,0,0,0,0,0,0,0,0,0,0,0,0,0,0,0,0,0,0,0,0,0,0,0,0,0,0,0,0,0,0,0,0,0,0,0,0,0,0,0,0,0,0,0,0,0,0,0,0,0,0,0,0,0,0,0,0,0,0,0,0,0,0,0,0,0,0,0,0,0,0,0,0,0,0,0,0,0,0,0,0,0,0,0,0,0,0,0,0,0,0,0,0,0,0,0,0,0,0,0,0,0,0,0,0,0,0,0,0,0,0,0,0,0,0,0,0,0,0,0,0,0,0,0,0,0,0,0,0,0,0,0,0,0,0,0,0,0,0,0,0,0,0,0,0,0,0,0,0,0,0,0,0,0,0,0,0,0,0,0,0,0,0,0,0,0,0,0,0,0,0,0,0,0,0,0,0,0,0,0,0,0,0,0,0,0,0,0,0,0,0,0,0,0,0,0,0,0,0,0,0,0,0,0,0,0,0,0,0,0,0,0,0,0,0,0,0,0,0,0,0,0,0,0,0,0,0,0,0,0,0,0,0,0,0,0,0,0,0,0,0,0,0,0,0,0,0,0,0,0,0,0,0,0,0,0,0,0,0,0,0,0,0,0,0,0,0,0,0,0,0,0,0,0,0,0,0,0,0,0,0,0,0,0,0,0,0,0,0,0,0,0,0,0,0,0,0,0,0,0,0,0,0,0,0,0,0,0,0,0,0,0,0,0,0,0,0,0,0,0,0,0,0,0,0,0,0,0,0,0,0,0,0,0,0,0,0,0,0,0,0,0,0,0,0,0,0,0,0,0,0,0,0,0,0,0,0,0,0,0,0,0,0,0,0,0,0,0,0,0,0,0,0,0,0,0,0,0,0,0,0,0,0,0,0,0,0,0,0,0,0,0,0,0,0,0,0,0,0,0,0,0,0,0,0,0,0,0,0,0,0,0,0,0,0,0,0,0,0,0,0,0,0,0,0,0,0,0,0,0,0,0,0,0,0,0,0,0,0,0,0,0,0,0,0,0,0,0,0,0,0,0,0,0,0,0,0,0,0,0,0,0,0,0,0,0,0,0,0,0,0,0,0,0,0],
"events":[
null,
{"id":1,"name":"EV001","note":"","pages":[{"conditions":{"actorId":1,"actorValid":false,"itemId":1,"itemValid":false,"selfSwitchCh":"A","selfSwitchValid":false,"switch1Id":1,"switch1Valid":false,"switch2Id":1,"switch2Valid":false,"variableId":1,"variableValid":false,"variableValue":0},"directionFix":false,"image":{"characterIndex":0,"characterName":"","direction":2,"pattern":0,"tileId":0},"list":[{"code":231,"indent":0,"parameters":[6,"갤러리 1",0,0,0,0,100,100,255,0]},{"code":250,"indent":0,"parameters":[{"name":"Chime1","volume":90,"pitch":100,"pan":0}]},{"code":101,"indent":0,"parameters":["",0,0,2]},{"code":401,"indent":0,"parameters":["지금까지의 사진을 볼 수 있는 갤러리 방입니다!"]},{"code":101,"indent":0,"parameters":["",0,0,2]},{"code":401,"indent":0,"parameters":["방향키 왼쪽 오른쪽으로 넘길 수 있고"]},{"code":101,"indent":0,"parameters":["",0,0,2]},{"code":401,"indent":0,"parameters":["1부터 9까지의 숫자를 눌러 더 자세히 볼 수 있습니다!"]},{"code":101,"indent":0,"parameters":["",0,0,2]},{"code":401,"indent":0,"parameters":["shift로 갤러리에서 나갈 수 있습니다!"]},{"code":123,"indent":0,"parameters":["A",0]},{"code":0,"indent":0,"parameters":[]}],"moveFrequency":3,"moveRoute":{"list":[{"code":0,"parameters":[]}],"repeat":true,"skippable":false,"wait":false},"moveSpeed":3,"moveType":0,"priorityType":0,"stepAnime":false,"through":false,"trigger":3,"walkAnime":true},{"conditions":{"actorId":1,"actorValid":false,"itemId":1,"itemValid":false,"selfSwitchCh":"A","selfSwitchValid":true,"switch1Id":1,"switch1Valid":false,"switch2Id":1,"switch2Valid":false,"variableId":1,"variableValid":false,"variableValue":0},"directionFix":false,"image":{"characterIndex":0,"characterName":"","direction":2,"pattern":0,"tileId":0},"list":[{"code":355,"indent":0,"parameters":["Input.keyMapper[49] = '1';"]},{"code":355,"indent":0,"parameters":["Input.keyMapper[50] = '2';"]},{"code":355,"indent":0,"parameters":["Input.keyMapper[51] = '3';"]},{"code":355,"indent":0,"parameters":["Input.keyMapper[52] = '4';"]},{"code":355,"indent":0,"parameters":["Input.keyMapper[53] = '5';"]},{"code":355,"indent":0,"parameters":["Input.keyMapper[54] = '6';"]},{"code":355,"indent":0,"parameters":["Input.keyMapper[55] = '7';"]},{"code":355,"indent":0,"parameters":["Input.keyMapper[56] = '8';"]},{"code":355,"indent":0,"parameters":["Input.keyMapper[57] = '9';"]},{"code":111,"indent":0,"parameters":[11,"left"]},{"code":230,"indent":1,"parameters":[15]},{"code":250,"indent":1,"parameters":[{"name":"Book2","volume":90,"pitch":100,"pan":0}]},{"code":231,"indent":1,"parameters":[6,"갤러리 9",0,0,0,0,100,100,255,0]},{"code":121,"indent":1,"parameters":[218,218,0]},{"code":0,"indent":1,"parameters":[]},{"code":412,"indent":0,"parameters":[]},{"code":111,"indent":0,"parameters":[11,"right"]},{"code":230,"indent":1,"parameters":[15]},{"code":250,"indent":1,"parameters":[{"name":"Book2","volume":90,"pitch":100,"pan":0}]},{"code":231,"indent":1,"parameters":[6,"갤러리 2",0,0,0,0,100,100,255,0]},{"code":121,"indent":1,"parameters":[211,211,0]},{"code":0,"indent":1,"parameters":[]},{"code":412,"indent":0,"parameters":[]},{"code":111,"indent":0,"parameters":[12,"Input.isPressed('1')"]},{"code":231,"indent":1,"parameters":[7,"호러 장실",0,0,0,0,100,100,255,0]},{"code":250,"indent":1,"parameters":[{"name":"Chime2","volume":90,"pitch":100,"pan":0}]},{"code":101,"indent":1,"parameters":["",0,2,2]},{"code":401,"indent":1,"parameters":[""]},{"code":235,"indent":1,"parameters":[7]},{"code":0,"indent":1,"parameters":[]},{"code":412,"indent":0,"parameters":[]},{"code":111,"indent":0,"parameters":[12,"Input.isPressed('2')"]},{"code":231,"indent":1,"parameters":[7,"호러장실",0,0,0,0,100,100,255,0]},{"code":250,"indent":1,"parameters":[{"name":"Chime2","volume":90,"pitch":100,"pan":0}]},{"code":101,"indent":1,"parameters":["",0,2,2]},{"code":401,"indent":1,"parameters":[""]},{"code":235,"indent":1,"parameters":[7]},{"code":0,"indent":1,"parameters":[]},{"code":412,"indent":0,"parameters":[]},{"code":111,"indent":0,"parameters":[12,"Input.isPressed('3')"]},{"code":231,"indent":1,"parameters":[7,"호러호러 장시ㅣㄹ",0,0,0,0,100,100,255,0]},{"code":250,"indent":1,"parameters":[{"name":"Chime2","volume":90,"pitch":100,"pan":0}]},{"code":101,"indent":1,"parameters":["",0,2,2]},{"code":401,"indent":1,"parameters":[""]},{"code":235,"indent":1,"parameters":[7]},{"code":0,"indent":1,"parameters":[]},{"code":412,"indent":0,"parameters":[]},{"code":111,"indent":0,"parameters":[12,"Input.isPressed('4')"]},{"code":231,"indent":1,"parameters":[7,"호러 띠용장실",0,0,0,0,100,100,255,0]},{"code":250,"indent":1,"parameters":[{"name":"Chime2","volume":90,"pitch":100,"pan":0}]},{"code":101,"indent":1,"parameters":["",0,2,2]},{"code":401,"indent":1,"parameters":[""]},{"code":235,"indent":1,"parameters":[7]},{"code":0,"indent":1,"parameters":[]},{"code":412,"indent":0,"parameters":[]},{"code":111,"indent":0,"parameters":[12,"Input.isPressed('5')"]},{"code":231,"indent":1,"parameters":[7,"상점(곰돌)",0,0,0,0,100,100,255,0]},{"code":250,"indent":1,"parameters":[{"name":"Chime2","volume":90,"pitch":100,"pan":0}]},{"code":101,"indent":1,"parameters":["",0,2,2]},{"code":401,"indent":1,"parameters":[""]},{"code":235,"indent":1,"parameters":[7]},{"code":0,"indent":1,"parameters":[]},{"code":412,"indent":0,"parameters":[]},{"code":111,"indent":0,"parameters":[12,"Input.isPressed('6')"]},{"code":231,"indent":1,"parameters":[7,"장실",0,0,0,0,100,100,255,0]},{"code":250,"indent":1,"parameters":[{"name":"Chime2","volume":90,"pitch":100,"pan":0}]},{"code":101,"indent":1,"parameters":["",0,2,2]},{"code":401,"indent":1,"parameters":[""]},{"code":235,"indent":1,"parameters":[7]},{"code":0,"indent":1,"parameters":[]},{"code":412,"indent":0,"parameters":[]},{"code":111,"indent":0,"parameters":[12,"Input.isPressed('7')"]},{"code":231,"indent":1,"parameters":[7,"장실(꿈)",0,0,0,0,100,100,255,0]},{"code":250,"indent":1,"parameters":[{"name":"Chime2","volume":90,"pitch":100,"pan":0}]},{"code":101,"indent":1,"parameters":["",0,2,2]},{"code":401,"indent":1,"parameters":[""]},{"code":235,"indent":1,"parameters":[7]},{"code":0,"indent":1,"parameters":[]},{"code":412,"indent":0,"parameters":[]},{"code":111,"indent":0,"parameters":[12,"Input.isPressed('8')"]},{"code":231,"indent":1,"parameters":[7,"욕실",0,0,0,0,100,100,255,0]},{"code":250,"indent":1,"parameters":[{"name":"Chime2","volume":90,"pitch":100,"pan":0}]},{"code":101,"indent":1,"parameters":["",0,2,2]},{"code":401,"indent":1,"parameters":[""]},{"code":235,"indent":1,"parameters":[7]},{"code":0,"indent":1,"parameters":[]},{"code":412,"indent":0,"parameters":[]},{"code":111,"indent":0,"parameters":[12,"Input.isPressed('9')"]},{"code":231,"indent":1,"parameters":[7,"상점",0,0,0,0,100,100,255,0]},{"code":250,"indent":1,"parameters":[{"name":"Chime2","volume":90,"pitch":100,"pan":0}]},{"code":101,"indent":1,"parameters":["",0,2,2]},{"code":401,"indent":1,"parameters":[""]},{"code":235,"indent":1,"parameters":[7]},{"code":0,"indent":1,"parameters":[]},{"code":412,"indent":0,"parameters":[]},{"code":111,"indent":0,"parameters":[11,"shift"]},{"code":235,"indent":1,"parameters":[1]},{"code":123,"indent":1,"parameters":["A",1]},{"code":0,"indent":1,"parameters":[]},{"code":412,"indent":0,"parameters":[]},{"code":111,"indent":0,"parameters":[11,"shift"]},{"code":230,"indent":1,"parameters":[15]},{"code":250,"indent":1,"parameters":[{"name":"Book1","volume":90,"pitch":100,"pan":0}]},{"code":201,"indent":1,"parameters":[0,171,8,1,2,0]},{"code":235,"indent":1,"parameters":[6]},{"code":211,"indent":1,"parameters":[1]},{"code":135,"indent":1,"parameters":[1]},{"code":121,"indent":1,"parameters":[211,211,1]},{"code":121,"indent":1,"parameters":[212,212,1]},{"code":121,"indent":1,"parameters":[213,213,1]},{"code":121,"indent":1,"parameters":[214,214,1]},{"code":121,"indent":1,"parameters":[215,215,1]},{"code":121,"indent":1,"parameters":[216,216,1]},{"code":121,"indent":1,"parameters":[217,217,1]},{"code":121,"indent":1,"parameters":[218,218,1]},{"code":123,"indent":1,"parameters":["A",1]},{"code":0,"indent":1,"parameters":[]},{"code":412,"indent":0,"parameters":[]},{"code":0,"indent":0,"parameters":[]}],"moveFrequency":3,"moveRoute":{"list":[{"code":0,"parameters":[]}],"repeat":true,"skippable":false,"wait":false},"moveSpeed":3,"moveType":0,"priorityType":0,"stepAnime":false,"through":false,"trigger":3,"walkAnime":true},{"conditions":{"actorId":1,"actorValid":false,"itemId":1,"itemValid":false,"selfSwitchCh":"A","selfSwitchValid":false,"switch1Id":211,"switch1Valid":true,"switch2Id":1,"switch2Valid":false,"variableId":1,"variableValid":false,"variableValue":0},"directionFix":false,"image":{"characterIndex":0,"characterName":"","direction":2,"pattern":0,"tileId":0},"list":[{"code":355,"indent":0,"parameters":["Input.keyMapper[49] = '1';"]},{"code":355,"indent":0,"parameters":["Input.keyMapper[50] = '2';"]},{"code":355,"indent":0,"parameters":["Input.keyMapper[51] = '3';"]},{"code":355,"indent":0,"parameters":["Input.keyMapper[52] = '4';"]},{"code":355,"indent":0,"parameters":["Input.keyMapper[53] = '5';"]},{"code":355,"indent":0,"parameters":["Input.keyMapper[54] = '6';"]},{"code":355,"indent":0,"parameters":["Input.keyMapper[55] = '7';"]},{"code":355,"indent":0,"parameters":["Input.keyMapper[56] = '8';"]},{"code":355,"indent":0,"parameters":["Input.keyMapper[57] = '9';"]},{"code":111,"indent":0,"parameters":[11,"left"]},{"code":230,"indent":1,"parameters":[15]},{"code":250,"indent":1,"parameters":[{"name":"Book2","volume":90,"pitch":100,"pan":0}]},{"code":231,"indent":1,"parameters":[6,"갤러리 1",0,0,0,0,100,100,255,0]},{"code":121,"indent":1,"parameters":[211,211,1]},{"code":0,"indent":1,"parameters":[]},{"code":412,"indent":0,"parameters":[]},{"code":111,"indent":0,"parameters":[11,"right"]},{"code":230,"indent":1,"parameters":[15]},{"code":250,"indent":1,"parameters":[{"name":"Book2","volume":90,"pitch":100,"pan":0}]},{"code":231,"indent":1,"parameters":[6,"갤러리 3",0,0,0,0,100,100,255,0]},{"code":121,"indent":1,"parameters":[212,212,0]},{"code":121,"indent":1,"parameters":[211,211,1]},{"code":0,"indent":1,"parameters":[]},{"code":412,"indent":0,"parameters":[]},{"code":111,"indent":0,"parameters":[12,"Input.isPressed('1')"]},{"code":231,"indent":1,"parameters":[7,"상점(꿈)",0,0,0,0,100,100,255,0]},{"code":250,"indent":1,"parameters":[{"name":"Chime2","volume":90,"pitch":100,"pan":0}]},{"code":101,"indent":1,"parameters":["",0,2,2]},{"code":401,"indent":1,"parameters":[""]},{"code":235,"indent":1,"parameters":[7]},{"code":0,"indent":1,"parameters":[]},{"code":412,"indent":0,"parameters":[]},{"code":111,"indent":0,"parameters":[12,"Input.isPressed('2')"]},{"code":231,"indent":1,"parameters":[7,"뒤틀린 상점",0,0,0,0,100,100,255,0]},{"code":250,"indent":1,"parameters":[{"name":"Chime2","volume":90,"pitch":100,"pan":0}]},{"code":101,"indent":1,"parameters":["",0,2,2]},{"code":401,"indent":1,"parameters":[""]},{"code":235,"indent":1,"parameters":[7]},{"code":0,"indent":1,"parameters":[]},{"code":412,"indent":0,"parameters":[]},{"code":111,"indent":0,"parameters":[12,"Input.isPressed('3')"]},{"code":231,"indent":1,"parameters":[7,"살자 거울",0,0,0,0,100,100,255,0]},{"code":250,"indent":1,"parameters":[{"name":"Chime2","volume":90,"pitch":100,"pan":0}]},{"code":101,"indent":1,"parameters":["",0,2,2]},{"code":401,"indent":1,"parameters":[""]},{"code":235,"indent":1,"parameters":[7]},{"code":0,"indent":1,"parameters":[]},{"code":412,"indent":0,"parameters":[]},{"code":111,"indent":0,"parameters":[12,"Input.isPressed('4')"]},{"code":231,"indent":1,"parameters":[7,"울거 아르시-스",0,0,0,0,100,100,255,0]},{"code":250,"indent":1,"parameters":[{"name":"Chime2","volume":90,"pitch":100,"pan":0}]},{"code":101,"indent":1,"parameters":["",0,2,2]},{"code":401,"indent":1,"parameters":[""]},{"code":235,"indent":1,"parameters":[7]},{"code":0,"indent":1,"parameters":[]},{"code":412,"indent":0,"parameters":[]},{"code":111,"indent":0,"parameters":[12,"Input.isPressed('5')"]},{"code":231,"indent":1,"parameters":[7,"아르시스 글리치",0,0,0,0,100,100,255,0]},{"code":250,"indent":1,"parameters":[{"name":"Chime2","volume":90,"pitch":100,"pan":0}]},{"code":101,"indent":1,"parameters":["",0,2,2]},{"code":401,"indent":1,"parameters":[""]},{"code":235,"indent":1,"parameters":[7]},{"code":0,"indent":1,"parameters":[]},{"code":412,"indent":0,"parameters":[]},{"code":111,"indent":0,"parameters":[12,"Input.isPressed('6')"]},{"code":231,"indent":1,"parameters":[7,"울거 달",0,0,0,0,100,100,255,0]},{"code":250,"indent":1,"parameters":[{"name":"Chime2","volume":90,"pitch":100,"pan":0}]},{"code":101,"indent":1,"parameters":["",0,2,2]},{"code":401,"indent":1,"parameters":[""]},{"code":235,"indent":1,"parameters":[7]},{"code":0,"indent":1,"parameters":[]},{"code":412,"indent":0,"parameters":[]},{"code":111,"indent":0,"parameters":[12,"Input.isPressed('7')"]},{"code":231,"indent":1,"parameters":[7,"칼방 자료화면!",0,0,0,0,100,100,255,0]},{"code":250,"indent":1,"parameters":[{"name":"Chime2","volume":90,"pitch":100,"pan":0}]},{"code":101,"indent":1,"parameters":["",0,2,2]},{"code":401,"indent":1,"parameters":[""]},{"code":235,"indent":1,"parameters":[7]},{"code":0,"indent":1,"parameters":[]},{"code":412,"indent":0,"parameters":[]},{"code":111,"indent":0,"parameters":[12,"Input.isPressed('8')"]},{"code":231,"indent":1,"parameters":[7,"으아악",0,0,0,0,100,100,255,0]},{"code":250,"indent":1,"parameters":[{"name":"Chime2","volume":90,"pitch":100,"pan":0}]},{"code":101,"indent":1,"parameters":["",0,2,2]},{"code":401,"indent":1,"parameters":[""]},{"code":235,"indent":1,"parameters":[7]},{"code":0,"indent":1,"parameters":[]},{"code":412,"indent":0,"parameters":[]},{"code":111,"indent":0,"parameters":[12,"Input.isPressed('9')"]},{"code":231,"indent":1,"parameters":[7,"시체",0,0,0,0,100,100,255,0]},{"code":250,"indent":1,"parameters":[{"name":"Chime2","volume":90,"pitch":100,"pan":0}]},{"code":101,"indent":1,"parameters":["",0,2,2]},{"code":401,"indent":1,"parameters":[""]},{"code":235,"indent":1,"parameters":[7]},{"code":0,"indent":1,"parameters":[]},{"code":412,"indent":0,"parameters":[]},{"code":111,"indent":0,"parameters":[11,"shift"]},{"code":230,"indent":1,"parameters":[15]},{"code":250,"indent":1,"parameters":[{"name":"Book1","volume":90,"pitch":100,"pan":0}]},{"code":201,"indent":1,"parameters":[0,171,8,1,2,0]},{"code":235,"indent":1,"parameters":[6]},{"code":211,"indent":1,"parameters":[1]},{"code":135,"indent":1,"parameters":[1]},{"code":121,"indent":1,"parameters":[211,211,1]},{"code":121,"indent":1,"parameters":[212,212,1]},{"code":121,"indent":1,"parameters":[213,213,1]},{"code":121,"indent":1,"parameters":[214,214,1]},{"code":121,"indent":1,"parameters":[215,215,1]},{"code":121,"indent":1,"parameters":[216,216,1]},{"code":121,"indent":1,"parameters":[217,217,1]},{"code":121,"indent":1,"parameters":[218,218,1]},{"code":123,"indent":1,"parameters":["A",1]},{"code":0,"indent":1,"parameters":[]},{"code":412,"indent":0,"parameters":[]},{"code":0,"indent":0,"parameters":[]}],"moveFrequency":3,"moveRoute":{"list":[{"code":0,"parameters":[]}],"repeat":true,"skippable":false,"wait":false},"moveSpeed":3,"moveType":0,"priorityType":0,"stepAnime":false,"through":false,"trigger":3,"walkAnime":true},{"conditions":{"actorId":1,"actorValid":false,"itemId":1,"itemValid":false,"selfSwitchCh":"A","selfSwitchValid":false,"switch1Id":212,"switch1Valid":true,"switch2Id":1,"switch2Valid":false,"variableId":1,"variableValid":false,"variableValue":0},"directionFix":false,"image":{"characterIndex":0,"characterName":"","direction":2,"pattern":0,"tileId":0},"list":[{"code":355,"indent":0,"parameters":["Input.keyMapper[49] = '1';"]},{"code":355,"indent":0,"parameters":["Input.keyMapper[50] = '2';"]},{"code":355,"indent":0,"parameters":["Input.keyMapper[51] = '3';"]},{"code":355,"indent":0,"parameters":["Input.keyMapper[52] = '4';"]},{"code":355,"indent":0,"parameters":["Input.keyMapper[53] = '5';"]},{"code":355,"indent":0,"parameters":["Input.keyMapper[54] = '6';"]},{"code":355,"indent":0,"parameters":["Input.keyMapper[55] = '7';"]},{"code":355,"indent":0,"parameters":["Input.keyMapper[56] = '8';"]},{"code":355,"indent":0,"parameters":["Input.keyMapper[57] = '9';"]},{"code":111,"indent":0,"parameters":[11,"left"]},{"code":230,"indent":1,"parameters":[15]},{"code":250,"indent":1,"parameters":[{"name":"Book2","volume":90,"pitch":100,"pan":0}]},{"code":231,"indent":1,"parameters":[6,"갤러리 2",0,0,0,0,100,100,255,0]},{"code":121,"indent":1,"parameters":[212,212,1]},{"code":121,"indent":1,"parameters":[211,211,0]},{"code":0,"indent":1,"parameters":[]},{"code":412,"indent":0,"parameters":[]},{"code":111,"indent":0,"parameters":[11,"right"]},{"code":230,"indent":1,"parameters":[15]},{"code":250,"indent":1,"parameters":[{"name":"Book2","volume":90,"pitch":100,"pan":0}]},{"code":231,"indent":1,"parameters":[6,"갤러리 4",0,0,0,0,100,100,255,0]},{"code":121,"indent":1,"parameters":[213,213,0]},{"code":121,"indent":1,"parameters":[212,212,1]},{"code":0,"indent":1,"parameters":[]},{"code":412,"indent":0,"parameters":[]},{"code":111,"indent":0,"parameters":[12,"Input.isPressed('1')"]},{"code":231,"indent":1,"parameters":[7,"오류창",0,0,0,0,100,100,255,0]},{"code":250,"indent":1,"parameters":[{"name":"Chime2","volume":90,"pitch":100,"pan":0}]},{"code":101,"indent":1,"parameters":["",0,2,2]},{"code":401,"indent":1,"parameters":[""]},{"code":235,"indent":1,"parameters":[7]},{"code":0,"indent":1,"parameters":[]},{"code":412,"indent":0,"parameters":[]},{"code":111,"indent":0,"parameters":[12,"Input.isPressed('2')"]},{"code":231,"indent":1,"parameters":[7,"엿보기",0,0,0,0,100,100,255,0]},{"code":250,"indent":1,"parameters":[{"name":"Chime2","volume":90,"pitch":100,"pan":0}]},{"code":101,"indent":1,"parameters":["",0,2,2]},{"code":401,"indent":1,"parameters":[""]},{"code":235,"indent":1,"parameters":[7]},{"code":0,"indent":1,"parameters":[]},{"code":412,"indent":0,"parameters":[]},{"code":111,"indent":0,"parameters":[12,"Input.isPressed('3')"]},{"code":231,"indent":1,"parameters":[7,"엿보기(호러)",0,0,0,0,100,100,255,0]},{"code":250,"indent":1,"parameters":[{"name":"Chime2","volume":90,"pitch":100,"pan":0}]},{"code":101,"indent":1,"parameters":["",0,2,2]},{"code":401,"indent":1,"parameters":[""]},{"code":235,"indent":1,"parameters":[7]},{"code":0,"indent":1,"parameters":[]},{"code":412,"indent":0,"parameters":[]},{"code":111,"indent":0,"parameters":[12,"Input.isPressed('4')"]},{"code":231,"indent":1,"parameters":[7,"야밤에 뭐지",0,0,0,0,100,100,255,0]},{"code":250,"indent":1,"parameters":[{"name":"Chime2","volume":90,"pitch":100,"pan":0}]},{"code":101,"indent":1,"parameters":["",0,2,2]},{"code":401,"indent":1,"parameters":[""]},{"code":235,"indent":1,"parameters":[7]},{"code":0,"indent":1,"parameters":[]},{"code":412,"indent":0,"parameters":[]},{"code":111,"indent":0,"parameters":[12,"Input.isPressed('5')"]},{"code":231,"indent":1,"parameters":[7,"도시",0,0,0,0,100,100,255,0]},{"code":250,"indent":1,"parameters":[{"name":"Chime2","volume":90,"pitch":100,"pan":0}]},{"code":101,"indent":1,"parameters":["",0,2,2]},{"code":401,"indent":1,"parameters":[""]},{"code":235,"indent":1,"parameters":[7]},{"code":0,"indent":1,"parameters":[]},{"code":412,"indent":0,"parameters":[]},{"code":111,"indent":0,"parameters":[12,"Input.isPressed('6')"]},{"code":231,"indent":1,"parameters":[7,"메모",0,0,0,0,100,100,255,0]},{"code":250,"indent":1,"parameters":[{"name":"Chime2","volume":90,"pitch":100,"pan":0}]},{"code":101,"indent":1,"parameters":["",0,2,2]},{"code":401,"indent":1,"parameters":[""]},{"code":235,"indent":1,"parameters":[7]},{"code":0,"indent":1,"parameters":[]},{"code":412,"indent":0,"parameters":[]},{"code":111,"indent":0,"parameters":[12,"Input.isPressed('7')"]},{"code":231,"indent":1,"parameters":[7,"메뉴판",0,0,0,0,100,100,255,0]},{"code":250,"indent":1,"parameters":[{"name":"Chime2","volume":90,"pitch":100,"pan":0}]},{"code":101,"indent":1,"parameters":["",0,2,2]},{"code":401,"indent":1,"parameters":[""]},{"code":235,"indent":1,"parameters":[7]},{"code":0,"indent":1,"parameters":[]},{"code":412,"indent":0,"parameters":[]},{"code":111,"indent":0,"parameters":[12,"Input.isPressed('8')"]},{"code":231,"indent":1,"parameters":[7,"눕",0,0,0,0,100,100,255,0]},{"code":250,"indent":1,"parameters":[{"name":"Chime2","volume":90,"pitch":100,"pan":0}]},{"code":101,"indent":1,"parameters":["",0,2,2]},{"code":401,"indent":1,"parameters":[""]},{"code":235,"indent":1,"parameters":[7]},{"code":0,"indent":1,"parameters":[]},{"code":412,"indent":0,"parameters":[]},{"code":111,"indent":0,"parameters":[12,"Input.isPressed('9')"]},{"code":231,"indent":1,"parameters":[7,"눕2",0,0,0,0,100,100,255,0]},{"code":250,"indent":1,"parameters":[{"name":"Chime2","volume":90,"pitch":100,"pan":0}]},{"code":101,"indent":1,"parameters":["",0,2,2]},{"code":401,"indent":1,"parameters":[""]},{"code":235,"indent":1,"parameters":[7]},{"code":0,"indent":1,"parameters":[]},{"code":412,"indent":0,"parameters":[]},{"code":111,"indent":0,"parameters":[11,"shift"]},{"code":230,"indent":1,"parameters":[15]},{"code":250,"indent":1,"parameters":[{"name":"Book1","volume":90,"pitch":100,"pan":0}]},{"code":201,"indent":1,"parameters":[0,171,8,1,2,0]},{"code":235,"indent":1,"parameters":[6]},{"code":211,"indent":1,"parameters":[1]},{"code":135,"indent":1,"parameters":[1]},{"code":121,"indent":1,"parameters":[211,211,1]},{"code":121,"indent":1,"parameters":[212,212,1]},{"code":121,"indent":1,"parameters":[213,213,1]},{"code":121,"indent":1,"parameters":[214,214,1]},{"code":121,"indent":1,"parameters":[215,215,1]},{"code":121,"indent":1,"parameters":[216,216,1]},{"code":121,"indent":1,"parameters":[217,217,1]},{"code":121,"indent":1,"parameters":[218,218,1]},{"code":123,"indent":1,"parameters":["A",1]},{"code":0,"indent":1,"parameters":[]},{"code":412,"indent":0,"parameters":[]},{"code":0,"indent":0,"parameters":[]}],"moveFrequency":3,"moveRoute":{"list":[{"code":0,"parameters":[]}],"repeat":true,"skippable":false,"wait":false},"moveSpeed":3,"moveType":0,"priorityType":0,"stepAnime":false,"through":false,"trigger":3,"walkAnime":true},{"conditions":{"actorId":1,"actorValid":false,"itemId":1,"itemValid":false,"selfSwitchCh":"A","selfSwitchValid":false,"switch1Id":213,"switch1Valid":true,"switch2Id":1,"switch2Valid":false,"variableId":1,"variableValid":false,"variableValue":0},"directionFix":false,"image":{"characterIndex":0,"characterName":"","direction":2,"pattern":0,"tileId":0},"list":[{"code":355,"indent":0,"parameters":["Input.keyMapper[49] = '1';"]},{"code":355,"indent":0,"parameters":["Input.keyMapper[50] = '2';"]},{"code":355,"indent":0,"parameters":["Input.keyMapper[51] = '3';"]},{"code":355,"indent":0,"parameters":["Input.keyMapper[52] = '4';"]},{"code":355,"indent":0,"parameters":["Input.keyMapper[53] = '5';"]},{"code":355,"indent":0,"parameters":["Input.keyMapper[54] = '6';"]},{"code":355,"indent":0,"parameters":["Input.keyMapper[55] = '7';"]},{"code":355,"indent":0,"parameters":["Input.keyMapper[56] = '8';"]},{"code":355,"indent":0,"parameters":["Input.keyMapper[57] = '9';"]},{"code":111,"indent":0,"parameters":[11,"left"]},{"code":230,"indent":1,"parameters":[15]},{"code":250,"indent":1,"parameters":[{"name":"Book2","volume":90,"pitch":100,"pan":0}]},{"code":231,"indent":1,"parameters":[6,"갤러리 3",0,0,0,0,100,100,255,0]},{"code":121,"indent":1,"parameters":[213,213,1]},{"code":121,"indent":1,"parameters":[212,212,0]},{"code":0,"indent":1,"parameters":[]},{"code":412,"indent":0,"parameters":[]},{"code":111,"indent":0,"parameters":[11,"right"]},{"code":230,"indent":1,"parameters":[15]},{"code":250,"indent":1,"parameters":[{"name":"Book2","volume":90,"pitch":100,"pan":0}]},{"code":231,"indent":1,"parameters":[6,"갤러리 5+",0,0,0,0,100,100,255,0]},{"code":121,"indent":1,"parameters":[213,213,1]},{"code":121,"indent":1,"parameters":[250,250,0]},{"code":0,"indent":1,"parameters":[]},{"code":412,"indent":0,"parameters":[]},{"code":111,"indent":0,"parameters":[12,"Input.isPressed('1')"]},{"code":231,"indent":1,"parameters":[7,"눈팜",0,0,0,0,100,100,255,0]},{"code":250,"indent":1,"parameters":[{"name":"Chime2","volume":90,"pitch":100,"pan":0}]},{"code":101,"indent":1,"parameters":["",0,2,2]},{"code":401,"indent":1,"parameters":[""]},{"code":235,"indent":1,"parameters":[7]},{"code":0,"indent":1,"parameters":[]},{"code":412,"indent":0,"parameters":[]},{"code":111,"indent":0,"parameters":[12,"Input.isPressed('2')"]},{"code":231,"indent":1,"parameters":[7,"KakaoTalk_20220128_221242581",0,0,0,0,100,100,255,0]},{"code":250,"indent":1,"parameters":[{"name":"Chime2","volume":90,"pitch":100,"pan":0}]},{"code":101,"indent":1,"parameters":["",0,2,2]},{"code":401,"indent":1,"parameters":[""]},{"code":235,"indent":1,"parameters":[7]},{"code":0,"indent":1,"parameters":[]},{"code":412,"indent":0,"parameters":[]},{"code":111,"indent":0,"parameters":[12,"Input.isPressed('3')"]},{"code":231,"indent":1,"parameters":[7,"KakaoTalk_20220128_221242581_01",0,0,0,0,100,100,255,0]},{"code":250,"indent":1,"parameters":[{"name":"Chime2","volume":90,"pitch":100,"pan":0}]},{"code":101,"indent":1,"parameters":["",0,2,2]},{"code":401,"indent":1,"parameters":[""]},{"code":235,"indent":1,"parameters":[7]},{"code":0,"indent":1,"parameters":[]},{"code":412,"indent":0,"parameters":[]},{"code":111,"indent":0,"parameters":[12,"Input.isPressed('4')"]},{"code":231,"indent":1,"parameters":[7,"낙낙서",0,0,0,0,100,100,255,0]},{"code":250,"indent":1,"parameters":[{"name":"Chime2","volume":90,"pitch":100,"pan":0}]},{"code":101,"indent":1,"parameters":["",0,2,2]},{"code":401,"indent":1,"parameters":[""]},{"code":235,"indent":1,"parameters":[7]},{"code":0,"indent":1,"parameters":[]},{"code":412,"indent":0,"parameters":[]},{"code":111,"indent":0,"parameters":[12,"Input.isPressed('5')"]},{"code":231,"indent":1,"parameters":[7,"낙서",0,0,0,0,100,100,255,0]},{"code":250,"indent":1,"parameters":[{"name":"Chime2","volume":90,"pitch":100,"pan":0}]},{"code":101,"indent":1,"parameters":["",0,2,2]},{"code":401,"indent":1,"parameters":[""]},{"code":235,"indent":1,"parameters":[7]},{"code":0,"indent":1,"parameters":[]},{"code":412,"indent":0,"parameters":[]},{"code":111,"indent":0,"parameters":[12,"Input.isPressed('6')"]},{"code":231,"indent":1,"parameters":[7,"이스터 에그",0,0,0,0,100,100,255,0]},{"code":250,"indent":1,"parameters":[{"name":"Chime2","volume":90,"pitch":100,"pan":0}]},{"code":101,"indent":1,"parameters":["",0,2,2]},{"code":401,"indent":1,"parameters":[""]},{"code":235,"indent":1,"parameters":[7]},{"code":0,"indent":1,"parameters":[]},{"code":412,"indent":0,"parameters":[]},{"code":111,"indent":0,"parameters":[12,"Input.isPressed('7')"]},{"code":231,"indent":1,"parameters":[7,"살자엔딩",0,0,0,0,100,100,255,0]},{"code":250,"indent":1,"parameters":[{"name":"Chime2","volume":90,"pitch":100,"pan":0}]},{"code":101,"indent":1,"parameters":["",0,2,2]},{"code":401,"indent":1,"parameters":[""]},{"code":235,"indent":1,"parameters":[7]},{"code":0,"indent":1,"parameters":[]},{"code":412,"indent":0,"parameters":[]},{"code":111,"indent":0,"parameters":[12,"Input.isPressed('8')"]},{"code":231,"indent":1,"parameters":[7,"마지막 1",0,0,0,0,100,100,255,0]},{"code":250,"indent":1,"parameters":[{"name":"Chime2","volume":90,"pitch":100,"pan":0}]},{"code":101,"indent":1,"parameters":["",0,2,2]},{"code":401,"indent":1,"parameters":[""]},{"code":235,"indent":1,"parameters":[7]},{"code":0,"indent":1,"parameters":[]},{"code":412,"indent":0,"parameters":[]},{"code":111,"indent":0,"parameters":[12,"Input.isPressed('9')"]},{"code":231,"indent":1,"parameters":[7,"타이틀",0,0,0,0,100,100,255,0]},{"code":250,"indent":1,"parameters":[{"name":"Chime2","volume":90,"pitch":100,"pan":0}]},{"code":101,"indent":1,"parameters":["",0,2,2]},{"code":401,"indent":1,"parameters":[""]},{"code":235,"indent":1,"parameters":[7]},{"code":0,"indent":1,"parameters":[]},{"code":412,"indent":0,"parameters":[]},{"code":111,"indent":0,"parameters":[11,"shift"]},{"code":230,"indent":1,"parameters":[15]},{"code":250,"indent":1,"parameters":[{"name":"Book1","volume":90,"pitch":100,"pan":0}]},{"code":201,"indent":1,"parameters":[0,171,8,1,2,0]},{"code":235,"indent":1,"parameters":[6]},{"code":211,"indent":1,"parameters":[1]},{"code":135,"indent":1,"parameters":[1]},{"code":121,"indent":1,"parameters":[211,211,1]},{"code":121,"indent":1,"parameters":[212,212,1]},{"code":121,"indent":1,"parameters":[213,213,1]},{"code":121,"indent":1,"parameters":[214,214,1]},{"code":121,"indent":1,"parameters":[215,215,1]},{"code":121,"indent":1,"parameters":[216,216,1]},{"code":121,"indent":1,"parameters":[217,217,1]},{"code":121,"indent":1,"parameters":[218,218,1]},{"code":123,"indent":1,"parameters":["A",1]},{"code":0,"indent":1,"parameters":[]},{"code":412,"indent":0,"parameters":[]},{"code":0,"indent":0,"parameters":[]}],"moveFrequency":3,"moveRoute":{"list":[{"code":0,"parameters":[]}],"repeat":true,"skippable":false,"wait":false},"moveSpeed":3,"moveType":0,"priorityType":0,"stepAnime":false,"through":false,"trigger":3,"walkAnime":true},{"conditions":{"actorId":1,"actorValid":false,"itemId":1,"itemValid":false,"selfSwitchCh":"A","selfSwitchValid":false,"switch1Id":250,"switch1Valid":true,"switch2Id":1,"switch2Valid":false,"variableId":1,"variableValid":false,"variableValue":0},"directionFix":false,"image":{"characterIndex":0,"characterName":"","direction":2,"pattern":0,"tileId":0},"list":[{"code":355,"indent":0,"parameters":["Input.keyMapper[49] = '1';"]},{"code":355,"indent":0,"parameters":["Input.keyMapper[50] = '2';"]},{"code":355,"indent":0,"parameters":["Input.keyMapper[51] = '3';"]},{"code":355,"indent":0,"parameters":["Input.keyMapper[52] = '4';"]},{"code":355,"indent":0,"parameters":["Input.keyMapper[53] = '5';"]},{"code":355,"indent":0,"parameters":["Input.keyMapper[54] = '6';"]},{"code":355,"indent":0,"parameters":["Input.keyMapper[55] = '7';"]},{"code":355,"indent":0,"parameters":["Input.keyMapper[56] = '8';"]},{"code":355,"indent":0,"parameters":["Input.keyMapper[57] = '9';"]},{"code":111,"indent":0,"parameters":[11,"left"]},{"code":230,"indent":1,"parameters":[15]},{"code":250,"indent":1,"parameters":[{"name":"Book2","volume":90,"pitch":100,"pan":0}]},{"code":231,"indent":1,"parameters":[6,"갤러리 4",0,0,0,0,100,100,255,0]},{"code":121,"indent":1,"parameters":[250,250,1]},{"code":121,"indent":1,"parameters":[213,213,0]},{"code":0,"indent":1,"parameters":[]},{"code":412,"indent":0,"parameters":[]},{"code":111,"indent":0,"parameters":[11,"right"]},{"code":230,"indent":1,"parameters":[15]},{"code":250,"indent":1,"parameters":[{"name":"Book2","volume":90,"pitch":100,"pan":0}]},{"code":231,"indent":1,"parameters":[6,"갤러리 5",0,0,0,0,100,100,255,0]},{"code":121,"indent":1,"parameters":[250,250,1]},{"code":121,"indent":1,"parameters":[214,214,0]},{"code":0,"indent":1,"parameters":[]},{"code":412,"indent":0,"parameters":[]},{"code":111,"indent":0,"parameters":[12,"Input.isPressed('1')"]},{"code":231,"indent":1,"parameters":[7,"타이틀 글리치",0,0,0,0,100,100,255,0]},{"code":250,"indent":1,"parameters":[{"name":"Chime2","volume":90,"pitch":100,"pan":0}]},{"code":101,"indent":1,"parameters":["",0,2,2]},{"code":401,"indent":1,"parameters":[""]},{"code":235,"indent":1,"parameters":[7]},{"code":0,"indent":1,"parameters":[]},{"code":412,"indent":0,"parameters":[]},{"code":111,"indent":0,"parameters":[12,"Input.isPressed('2')"]},{"code":231,"indent":1,"parameters":[7,"깨진 타이틀",0,0,0,0,100,100,255,0]},{"code":250,"indent":1,"parameters":[{"name":"Chime2","volume":90,"pitch":100,"pan":0}]},{"code":101,"indent":1,"parameters":["",0,2,2]},{"code":401,"indent":1,"parameters":[""]},{"code":235,"indent":1,"parameters":[7]},{"code":0,"indent":1,"parameters":[]},{"code":412,"indent":0,"parameters":[]},{"code":111,"indent":0,"parameters":[12,"Input.isPressed('3')"]},{"code":231,"indent":1,"parameters":[7,"살자 타이틀",0,0,0,0,100,100,255,0]},{"code":250,"indent":1,"parameters":[{"name":"Chime2","volume":90,"pitch":100,"pan":0}]},{"code":101,"indent":1,"parameters":["",0,2,2]},{"code":401,"indent":1,"parameters":[""]},{"code":235,"indent":1,"parameters":[7]},{"code":0,"indent":1,"parameters":[]},{"code":412,"indent":0,"parameters":[]},{"code":111,"indent":0,"parameters":[12,"Input.isPressed('4')"]},{"code":231,"indent":1,"parameters":[7,"타이틀22",0,0,0,0,100,100,255,0]},{"code":250,"indent":1,"parameters":[{"name":"Chime2","volume":90,"pitch":100,"pan":0}]},{"code":101,"indent":1,"parameters":["",0,2,2]},{"code":401,"indent":1,"parameters":[""]},{"code":235,"indent":1,"parameters":[7]},{"code":0,"indent":1,"parameters":[]},{"code":412,"indent":0,"parameters":[]},{"code":111,"indent":0,"parameters":[12,"Input.isPressed('5')"]},{"code":231,"indent":1,"parameters":[7,"메모2",0,0,0,0,100,100,255,0]},{"code":250,"indent":1,"parameters":[{"name":"Chime2","volume":90,"pitch":100,"pan":0}]},{"code":101,"indent":1,"parameters":["",0,2,2]},{"code":401,"indent":1,"parameters":[""]},{"code":235,"indent":1,"parameters":[7]},{"code":0,"indent":1,"parameters":[]},{"code":412,"indent":0,"parameters":[]},{"code":111,"indent":0,"parameters":[12,"Input.isPressed('6')"]},{"code":231,"indent":1,"parameters":[7,"안내",0,0,0,0,100,100,255,0]},{"code":250,"indent":1,"parameters":[{"name":"Chime2","volume":90,"pitch":100,"pan":0}]},{"code":101,"indent":1,"parameters":["",0,2,2]},{"code":401,"indent":1,"parameters":[""]},{"code":235,"indent":1,"parameters":[7]},{"code":0,"indent":1,"parameters":[]},{"code":412,"indent":0,"parameters":[]},{"code":111,"indent":0,"parameters":[12,"Input.isPressed('7')"]},{"code":0,"indent":1,"parameters":[]},{"code":412,"indent":0,"parameters":[]},{"code":111,"indent":0,"parameters":[12,"Input.isPressed('8')"]},{"code":0,"indent":1,"parameters":[]},{"code":412,"indent":0,"parameters":[]},{"code":111,"indent":0,"parameters":[12,"Input.isPressed('9')"]},{"code":0,"indent":1,"parameters":[]},{"code":412,"indent":0,"parameters":[]},{"code":111,"indent":0,"parameters":[11,"shift"]},{"code":230,"indent":1,"parameters":[15]},{"code":250,"indent":1,"parameters":[{"name":"Book1","volume":90,"pitch":100,"pan":0}]},{"code":201,"indent":1,"parameters":[0,171,8,1,2,0]},{"code":235,"indent":1,"parameters":[6]},{"code":211,"indent":1,"parameters":[1]},{"code":135,"indent":1,"parameters":[1]},{"code":121,"indent":1,"parameters":[211,211,1]},{"code":121,"indent":1,"parameters":[212,212,1]},{"code":121,"indent":1,"parameters":[213,213,1]},{"code":121,"indent":1,"parameters":[214,214,1]},{"code":121,"indent":1,"parameters":[215,215,1]},{"code":121,"indent":1,"parameters":[216,216,1]},{"code":121,"indent":1,"parameters":[217,217,1]},{"code":121,"indent":1,"parameters":[218,218,1]},{"code":123,"indent":1,"parameters":["A",1]},{"code":0,"indent":1,"parameters":[]},{"code":412,"indent":0,"parameters":[]},{"code":0,"indent":0,"parameters":[]}],"moveFrequency":3,"moveRoute":{"list":[{"code":0,"parameters":[]}],"repeat":true,"skippable":false,"wait":false},"moveSpeed":3,"moveType":0,"priorityType":0,"stepAnime":false,"through":false,"trigger":3,"walkAnime":true},{"conditions":{"actorId":1,"actorValid":false,"itemId":1,"itemValid":false,"selfSwitchCh":"A","selfSwitchValid":false,"switch1Id":214,"switch1Valid":true,"switch2Id":1,"switch2Valid":false,"variableId":1,"variableValid":false,"variableValue":0},"directionFix":false,"image":{"characterIndex":0,"characterName":"","direction":2,"pattern":0,"tileId":0},"list":[{"code":111,"indent":0,"parameters":[11,"left"]},{"code":230,"indent":1,"parameters":[15]},{"code":250,"indent":1,"parameters":[{"name":"Book2","volume":90,"pitch":100,"pan":0}]},{"code":231,"indent":1,"parameters":[6,"갤러리 5+",0,0,0,0,100,100,255,0]},{"code":121,"indent":1,"parameters":[214,214,1]},{"code":121,"indent":1,"parameters":[250,250,0]},{"code":0,"indent":1,"parameters":[]},{"code":412,"indent":0,"parameters":[]},{"code":111,"indent":0,"parameters":[11,"right"]},{"code":230,"indent":1,"parameters":[15]},{"code":250,"indent":1,"parameters":[{"name":"Book2","volume":90,"pitch":100,"pan":0}]},{"code":231,"indent":1,"parameters":[6,"갤러리 6",0,0,0,0,100,100,255,0]},{"code":121,"indent":1,"parameters":[214,214,1]},{"code":121,"indent":1,"parameters":[215,215,0]},{"code":0,"indent":1,"parameters":[]},{"code":412,"indent":0,"parameters":[]},{"code":111,"indent":0,"parameters":[11,"shift"]},{"code":230,"indent":1,"parameters":[15]},{"code":250,"indent":1,"parameters":[{"name":"Book1","volume":90,"pitch":100,"pan":0}]},{"code":201,"indent":1,"parameters":[0,171,8,1,2,0]},{"code":235,"indent":1,"parameters":[6]},{"code":211,"indent":1,"parameters":[1]},{"code":135,"indent":1,"parameters":[1]},{"code":121,"indent":1,"parameters":[211,211,1]},{"code":121,"indent":1,"parameters":[212,212,1]},{"code":121,"indent":1,"parameters":[213,213,1]},{"code":121,"indent":1,"parameters":[214,214,1]},{"code":121,"indent":1,"parameters":[215,215,1]},{"code":121,"indent":1,"parameters":[216,216,1]},{"code":121,"indent":1,"parameters":[217,217,1]},{"code":121,"indent":1,"parameters":[218,218,1]},{"code":123,"indent":1,"parameters":["A",1]},{"code":0,"indent":1,"parameters":[]},{"code":412,"indent":0,"parameters":[]},{"code":0,"indent":0,"parameters":[]}],"moveFrequency":3,"moveRoute":{"list":[{"code":0,"parameters":[]}],"repeat":true,"skippable":false,"wait":false},"moveSpeed":3,"moveType":0,"priorityType":0,"stepAnime":false,"through":false,"trigger":3,"walkAnime":true},{"conditions":{"actorId":1,"actorValid":false,"itemId":1,"itemValid":false,"selfSwitchCh":"A","selfSwitchValid":false,"switch1Id":215,"switch1Valid":true,"switch2Id":1,"switch2Valid":false,"variableId":1,"variableValid":false,"variableValue":0},"directionFix":false,"image":{"characterIndex":0,"characterName":"","direction":2,"pattern":0,"tileId":0},"list":[{"code":111,"indent":0,"parameters":[11,"left"]},{"code":230,"indent":1,"parameters":[15]},{"code":250,"indent":1,"parameters":[{"name":"Book2","volume":90,"pitch":100,"pan":0}]},{"code":231,"indent":1,"parameters":[6,"갤러리 5",0,0,0,0,100,100,255,0]},{"code":121,"indent":1,"parameters":[215,215,1]},{"code":121,"indent":1,"parameters":[214,214,0]},{"code":0,"indent":1,"parameters":[]},{"code":412,"indent":0,"parameters":[]},{"code":111,"indent":0,"parameters":[11,"right"]},{"code":230,"indent":1,"parameters":[15]},{"code":250,"indent":1,"parameters":[{"name":"Book2","volume":90,"pitch":100,"pan":0}]},{"code":231,"indent":1,"parameters":[6,"갤러리 7",0,0,0,0,100,100,255,0]},{"code":121,"indent":1,"parameters":[215,215,1]},{"code":121,"indent":1,"parameters":[216,216,0]},{"code":0,"indent":1,"parameters":[]},{"code":412,"indent":0,"parameters":[]},{"code":111,"indent":0,"parameters":[11,"shift"]},{"code":230,"indent":1,"parameters":[15]},{"code":250,"indent":1,"parameters":[{"name":"Book1","volume":90,"pitch":100,"pan":0}]},{"code":201,"indent":1,"parameters":[0,171,8,1,2,0]},{"code":235,"indent":1,"parameters":[6]},{"code":211,"indent":1,"parameters":[1]},{"code":135,"indent":1,"parameters":[1]},{"code":121,"indent":1,"parameters":[211,211,1]},{"code":121,"indent":1,"parameters":[212,212,1]},{"code":121,"indent":1,"parameters":[213,213,1]},{"code":121,"indent":1,"parameters":[214,214,1]},{"code":121,"indent":1,"parameters":[215,215,1]},{"code":121,"indent":1,"parameters":[216,216,1]},{"code":121,"indent":1,"parameters":[217,217,1]},{"code":121,"indent":1,"parameters":[218,218,1]},{"code":123,"indent":1,"parameters":["A",1]},{"code":0,"indent":1,"parameters":[]},{"code":412,"indent":0,"parameters":[]},{"code":0,"indent":0,"parameters":[]}],"moveFrequency":3,"moveRoute":{"list":[{"code":0,"parameters":[]}],"repeat":true,"skippable":false,"wait":false},"moveSpeed":3,"moveType":0,"priorityType":0,"stepAnime":false,"through":false,"trigger":3,"walkAnime":true},{"conditions":{"actorId":1,"actorValid":false,"itemId":1,"itemValid":false,"selfSwitchCh":"A","selfSwitchValid":false,"switch1Id":216,"switch1Valid":true,"switch2Id":1,"switch2Valid":false,"variableId":1,"variableValid":false,"variableValue":0},"directionFix":false,"image":{"characterIndex":0,"characterName":"","direction":2,"pattern":0,"tileId":0},"list":[{"code":111,"indent":0,"parameters":[11,"left"]},{"code":230,"indent":1,"parameters":[15]},{"code":250,"indent":1,"parameters":[{"name":"Book2","volume":90,"pitch":100,"pan":0}]},{"code":231,"indent":1,"parameters":[6,"갤러리 6",0,0,0,0,100,100,255,0]},{"code":121,"indent":1,"parameters":[216,216,1]},{"code":121,"indent":1,"parameters":[215,215,0]},{"code":0,"indent":1,"parameters":[]},{"code":412,"indent":0,"parameters":[]},{"code":111,"indent":0,"parameters":[11,"right"]},{"code":230,"indent":1,"parameters":[15]},{"code":250,"indent":1,"parameters":[{"name":"Book2","volume":90,"pitch":100,"pan":0}]},{"code":231,"indent":1,"parameters":[6,"갤러리 8",0,0,0,0,100,100,255,0]},{"code":121,"indent":1,"parameters":[216,216,1]},{"code":121,"indent":1,"parameters":[217,217,0]},{"code":0,"indent":1,"parameters":[]},{"code":412,"indent":0,"parameters":[]},{"code":111,"indent":0,"parameters":[11,"shift"]},{"code":230,"indent":1,"parameters":[15]},{"code":250,"indent":1,"parameters":[{"name":"Book1","volume":90,"pitch":100,"pan":0}]},{"code":201,"indent":1,"parameters":[0,171,8,1,2,0]},{"code":235,"indent":1,"parameters":[6]},{"code":211,"indent":1,"parameters":[1]},{"code":135,"indent":1,"parameters":[1]},{"code":121,"indent":1,"parameters":[211,211,1]},{"code":121,"indent":1,"parameters":[212,212,1]},{"code":121,"indent":1,"parameters":[213,213,1]},{"code":121,"indent":1,"parameters":[214,214,1]},{"code":121,"indent":1,"parameters":[215,215,1]},{"code":121,"indent":1,"parameters":[216,216,1]},{"code":121,"indent":1,"parameters":[217,217,1]},{"code":121,"indent":1,"parameters":[218,218,1]},{"code":123,"indent":1,"parameters":["A",1]},{"code":0,"indent":1,"parameters":[]},{"code":412,"indent":0,"parameters":[]},{"code":0,"indent":0,"parameters":[]}],"moveFrequency":3,"moveRoute":{"list":[{"code":0,"parameters":[]}],"repeat":true,"skippable":false,"wait":false},"moveSpeed":3,"moveType":0,"priorityType":0,"stepAnime":false,"through":false,"trigger":3,"walkAnime":true},{"conditions":{"actorId":1,"actorValid":false,"itemId":1,"itemValid":false,"selfSwitchCh":"A","selfSwitchValid":false,"switch1Id":217,"switch1Valid":true,"switch2Id":1,"switch2Valid":false,"variableId":1,"variableValid":false,"variableValue":0},"directionFix":false,"image":{"characterIndex":0,"characterName":"","direction":2,"pattern":0,"tileId":0},"list":[{"code":111,"indent":0,"parameters":[11,"left"]},{"code":230,"indent":1,"parameters":[15]},{"code":250,"indent":1,"parameters":[{"name":"Book2","volume":90,"pitch":100,"pan":0}]},{"code":231,"indent":1,"parameters":[6,"갤러리 7",0,0,0,0,100,100,255,0]},{"code":121,"indent":1,"parameters":[217,217,1]},{"code":121,"indent":1,"parameters":[216,216,0]},{"code":0,"indent":1,"parameters":[]},{"code":412,"indent":0,"parameters":[]},{"code":111,"indent":0,"parameters":[11,"right"]},{"code":230,"indent":1,"parameters":[15]},{"code":250,"indent":1,"parameters":[{"name":"Book2","volume":90,"pitch":100,"pan":0}]},{"code":231,"indent":1,"parameters":[6,"갤러리 9",0,0,0,0,100,100,255,0]},{"code":121,"indent":1,"parameters":[217,217,1]},{"code":121,"indent":1,"parameters":[218,218,0]},{"code":0,"indent":1,"parameters":[]},{"code":412,"indent":0,"parameters":[]},{"code":111,"indent":0,"parameters":[11,"shift"]},{"code":230,"indent":1,"parameters":[15]},{"code":250,"indent":1,"parameters":[{"name":"Book1","volume":90,"pitch":100,"pan":0}]},{"code":201,"indent":1,"parameters":[0,171,8,1,2,0]},{"code":235,"indent":1,"parameters":[6]},{"code":211,"indent":1,"parameters":[1]},{"code":135,"indent":1,"parameters":[1]},{"code":121,"indent":1,"parameters":[211,211,1]},{"code":121,"indent":1,"parameters":[212,212,1]},{"code":121,"indent":1,"parameters":[213,213,1]},{"code":121,"indent":1,"parameters":[214,214,1]},{"code":121,"indent":1,"parameters":[215,215,1]},{"code":121,"indent":1,"parameters":[216,216,1]},{"code":121,"indent":1,"parameters":[217,217,1]},{"code":121,"indent":1,"parameters":[218,218,1]},{"code":123,"indent":1,"parameters":["A",1]},{"code":0,"indent":1,"parameters":[]},{"code":412,"indent":0,"parameters":[]},{"code":0,"indent":0,"parameters":[]}],"moveFrequency":3,"moveRoute":{"list":[{"code":0,"parameters":[]}],"repeat":true,"skippable":false,"wait":false},"moveSpeed":3,"moveType":0,"priorityType":0,"stepAnime":false,"through":false,"trigger":3,"walkAnime":true},{"conditions":{"actorId":1,"actorValid":false,"itemId":1,"itemValid":false,"selfSwitchCh":"A","selfSwitchValid":false,"switch1Id":218,"switch1Valid":true,"switch2Id":1,"switch2Valid":false,"variableId":1,"variableValid":false,"variableValue":0},"directionFix":false,"image":{"characterIndex":0,"characterName":"","direction":2,"pattern":0,"tileId":0},"list":[{"code":111,"indent":0,"parameters":[11,"left"]},{"code":230,"indent":1,"parameters":[15]},{"code":250,"indent":1,"parameters":[{"name":"Book2","volume":90,"pitch":100,"pan":0}]},{"code":231,"indent":1,"parameters":[6,"갤러리 8",0,0,0,0,100,100,255,0]},{"code":121,"indent":1,"parameters":[218,218,1]},{"code":121,"indent":1,"parameters":[217,217,0]},{"code":0,"indent":1,"parameters":[]},{"code":412,"indent":0,"parameters":[]},{"code":111,"indent":0,"parameters":[11,"right"]},{"code":230,"indent":1,"parameters":[15]},{"code":250,"indent":1,"parameters":[{"name":"Book2","volume":90,"pitch":100,"pan":0}]},{"code":231,"indent":1,"parameters":[6,"갤러리 1",0,0,0,0,100,100,255,0]},{"code":121,"indent":1,"parameters":[218,218,1]},{"code":0,"indent":1,"parameters":[]},{"code":412,"indent":0,"parameters":[]},{"code":111,"indent":0,"parameters":[11,"shift"]},{"code":230,"indent":1,"parameters":[15]},{"code":250,"indent":1,"parameters":[{"name":"Book1","volume":90,"pitch":100,"pan":0}]},{"code":201,"indent":1,"parameters":[0,171,8,1,2,0]},{"code":235,"indent":1,"parameters":[6]},{"code":211,"indent":1,"parameters":[1]},{"code":135,"indent":1,"parameters":[1]},{"code":121,"indent":1,"parameters":[211,211,1]},{"code":121,"indent":1,"parameters":[212,212,1]},{"code":121,"indent":1,"parameters":[213,213,1]},{"code":121,"indent":1,"parameters":[214,214,1]},{"code":121,"indent":1,"parameters":[215,215,1]},{"code":121,"indent":1,"parameters":[216,216,1]},{"code":121,"indent":1,"parameters":[217,217,1]},{"code":121,"indent":1,"parameters":[218,218,1]},{"code":123,"indent":1,"parameters":["A",1]},{"code":0,"indent":1,"parameters":[]},{"code":412,"indent":0,"parameters":[]},{"code":0,"indent":0,"parameters":[]}],"moveFrequency":3,"moveRoute":{"list":[{"code":0,"parameters":[]}],"repeat":true,"skippable":false,"wait":false},"moveSpeed":3,"moveType":0,"priorityType":0,"stepAnime":false,"through":false,"trigger":3,"walkAnime":true}],"x":0,"y":0}
]
}